laundromat
tests
