Metadata-Version: 1.1
Name: streamr-infra-laundromat
Version: 0.0.4
Summary: Library to clean PR infra
Home-page: https://github.com/streamr-dev/streamr-infra-laundromat
Author: Streamr
Author-email: contact@streamr.com
License: UNKNOWN
Platform: UNKNOWN
Classifier: Programming Language :: Python :: 3
Classifier: License :: OSI Approved :: MIT License
Classifier: Operating System :: OS Independent
